video_clip_describer/__init__.py
video_clip_describer/cli.py
video_clip_describer/const.py
video_clip_describer/version.py
video_clip_describer/vision.py
video_clip_describer-0.4.0.dist-info/METADATA
video_clip_describer-0.4.0.dist-info/WHEEL
video_clip_describer-0.4.0.dist-info/entry_points.txt
video_clip_describer-0.4.0.dist-info/RECORD
