Metadata-Version: 2.1
Name: video-clip-describer
Version: 0.4.0
Summary: Generate text descriptions of video clips
License: MIT
Author: Bendik R. Brenne
Author-email: bendik@konstant.no
Requires-Python: >=3.12,<4.0
Classifier: Intended Audience :: Developers
Classifier: License :: OSI Approved :: MIT License
Classifier: Programming Language :: Python
Classifier: Programming Language :: Python :: 3
Classifier: Programming Language :: Python :: 3.12
Classifier: Programming Language :: Python :: 3.13
Requires-Dist: imagehash (>=4.3.1,<5.0.0)
Requires-Dist: openai (>=1.54.3,<2.0.0)
Requires-Dist: opencv-python-headless (>=4.10.0.84,<5.0.0.0)
Requires-Dist: typer (>=0.13.0,<0.14.0)
